albatross/__init__.py
albatross/compat.py
albatross/data_types.py
albatross/http_error.py
albatross/request.py
albatross/response.py
albatross/server.py
albatross/status_codes.py
albatross3-0.6.3.dist-info/DESCRIPTION.rst
albatross3-0.6.3.dist-info/METADATA
albatross3-0.6.3.dist-info/RECORD
albatross3-0.6.3.dist-info/WHEEL
albatross3-0.6.3.dist-info/metadata.json
albatross3-0.6.3.dist-info/top_level.txt
