Metadata-Version: 2.0
Name: albatross3
Version: 0.6.3
Summary: A modern async python3 web framework
Home-page: https://github.com/kespindler/albatross
Author: Kurt Spindler
Author-email: kespindler@gmail.com
License: MIT
Keywords: web http server async
Platform: UNKNOWN
Classifier: Development Status :: 3 - Alpha
Classifier: Intended Audience :: Developers
Classifier: License :: OSI Approved :: MIT License
Classifier: Programming Language :: Python :: 3.5
Requires-Dist: httptools
Provides-Extra: ujson
Requires-Dist: ujson; extra == 'ujson'
